face_lib/BlazeDetector.py
face_lib/__init__.py
face_lib/blazeFaceUtils.py
face_lib/download.py
face_lib/face_detection_back_256x256.onnx
face_lib/face_detection_front_128x128.onnx
face_lib/face_lib.py
face_lib/parse_url.py
face_library-1.1.3.dist-info/LICENSE
face_library-1.1.3.dist-info/METADATA
face_library-1.1.3.dist-info/WHEEL
face_library-1.1.3.dist-info/top_level.txt
face_library-1.1.3.dist-info/RECORD
