Metadata-Version: 2.1
Name: face-library
Version: 1.1.3
Summary: Face Library is an open source package for accurate and real-time face detection and recognition
Home-page: https://github.com/a-akram-98/face_lib
Author: Abdelrahman Akram
Author-email: a.akram.9821@gmail.com
License: UNKNOWN
Project-URL: Bug Tracker, https://github.com/a-akram-98/face_lib/issues
Platform: UNKNOWN
Classifier: Development Status :: 5 - Production/Stable
Classifier: Intended Audience :: Developers
Classifier: Programming Language :: Python
Classifier: Programming Language :: Python :: 3
Classifier: Programming Language :: Python :: 3 :: Only
Classifier: Programming Language :: Python :: 3.6
Classifier: Programming Language :: Python :: 3.7
Classifier: Programming Language :: Python :: 3.8
Classifier: Programming Language :: Python :: 3.9
Classifier: License :: OSI Approved :: MIT License
Classifier: Operating System :: OS Independent
Classifier: Topic :: Scientific/Engineering
Classifier: Topic :: Scientific/Engineering :: Artificial Intelligence
Classifier: Topic :: Scientific/Engineering :: Image Recognition
Classifier: Intended Audience :: Education
Classifier: Intended Audience :: Information Technology
Classifier: Intended Audience :: Science/Research
Classifier: Environment :: Console
Requires-Python: >=3.6
License-File: LICENSE
Requires-Dist: tqdm
Requires-Dist: requests[socks] (>=2.12.0)
Requires-Dist: six
Requires-Dist: numpy
Requires-Dist: opencv-python (>=4.5.3)
Requires-Dist: onnxruntime (>=1.9.0)
